<xml>
   <trace_no></trace_no>
   <ins_cd></ins_cd>
   <sub_ins_cd></sub_ins_cd>
   <mchnt_name></mchnt_name>
   <mchnt_shortname></mchnt_shortname>
   <real_name></real_name>
   <license_type>A</license_type>
   <license_no></license_no>
   <license_expire_dt></license_expire_dt>
   <certif_id></certif_id>
   <certif_id_expire_dt></certif_id_expire_dt>
   <contact_person></contact_person>
   <contact_phone></contact_phone>
   <contact_addr></contact_addr>
   <contact_mobile></contact_mobile>
   <contact_email></contact_email>
   <business>56</business>
   <city_cd></city_cd>
   <county_cd></county_cd>
   <acnt_type>2</acnt_type>
   <bank_type></bank_type>
   <inter_bank_no></inter_bank_no>
   <iss_bank_nm></iss_bank_nm>
   <acnt_nm></acnt_nm>
   <acnt_no></acnt_no>
   <settle_tp>1</settle_tp>
   <artif_nm></artif_nm>
   <acnt_artif_flag>1</acnt_artif_flag>
   <acnt_certif_tp>0</acnt_certif_tp>
   <acnt_certif_id></acnt_certif_id>
   <acnt_certif_expire_dt></acnt_certif_expire_dt>
   <acnt_contact_mobile></acnt_contact_mobile>
   <th_flag>0</th_flag>
   <wx_busi_flag>0</wx_busi_flag>
   <wx_flag>1</wx_flag>
   <wx_set_cd>M0000</wx_set_cd>
   <ali_flag>1</ali_flag>
   <ali_set_cd>M0000</ali_set_cd>
   <qpay_flag></qpay_flag>
   <qpay_set_cd></qpay_set_cd>
   <jdpay_flag></jdpay_flag>
   <jdpay_set_cd></jdpay_set_cd>
   <settle_tp_cd></settle_tp_cd>
   <settle_ts></settle_ts>
   <has_reserve_acnt></has_reserve_acnt>
   <reserve_acnt_no></reserve_acnt_no>
   <reserve_acnt_nm></reserve_acnt_nm>
   <reserve_inter_bank_no></reserve_inter_bank_no>
   <reserve_iss_bank_nm></reserve_iss_bank_nm>
   <reserve_bank_type></reserve_bank_type>
   <contact_cert_no></contact_cert_no>
   <license_start_dt></license_start_dt>
   <lic_regis_addr></lic_regis_addr>
   <card_start_dt></card_start_dt>
   <certif_phone></certif_phone>
   <sign></sign>
</xml>